Workbook

Sheet Raw_Data
A1: Semiconductor Peer Group – FY2023 Raw Financial Data (USD Millions) — SOURCE DATA ONLY
A2: Company | B2: Revenue ($M) | C2: COGS ($M) | D2: Accounts Receivable ($M) | E2: Inventory ($M) | F2: Cash & ST Investments ($M) | G2: Total Current Assets ($M) | H2: Accounts Payable ($M) | I2: Total Current Liabilities ($M) | J2: Operating Cash Flow ($M) | K2: Fiscal Year End
A3: AMD | B3: 22680 | C3: 11529 | D3: 2558 | E3: 1848 | F3: 5773 | G3: 12084 | H3: 1397 | I3: 4538 | J3: 2817 | K3: Dec 2023
A4: Intel | B4: 54228 | C4: 29134 | D4: 3039 | E4: 11127 | F4: 25020 | G4: 43273 | H4: 3987 | I4: 28053 | J4: 11518 | K4: Dec 2023
A5: Texas Instruments | B5: 17519 | C5: 5679 | D5: 813 | E5: 3812 | F5: 8474 | G5: 11497 | H5: 347 | I5: 2632 | J5: 6334 | K5: Dec 2023
A6: NVIDIA | B6: 60922 | C6: 16621 | D6: 9999 | E6: 5282 | F6: 25984 | G6: 46200 | H6: 1306 | I6: 10631 | J6: 28080 | K6: Jan 2024
A7: Qualcomm | B7: 35820 | C7: 16040 | D7: 2040 | E7: 2313 | F7: 8520 | G7: 14049 | H7: 791 | I7: 9016 | J7: 10133 | K7: Sep 2023
A8: NXP Semi | B8: 13276 | C8: 6146 | D8: 1091 | E8: 1700 | F8: 3276 | G8: 6504 | H8: 696 | I8: 3709 | J8: 3281 | K8: Dec 2023
A9: TSMC | B9: 69299 | C9: 31608 | D9: 4208 | E9: 6519 | F9: 35050 | G9: 46350 | H9: 3523 | I9: 25100 | J9: 37200 | K9: Dec 2023
A10: Micron | B10: 15540 | C10: 13974 | D10: 2388 | E10: 8032 | F10: 9830 | G10: 15070 | H10: 701 | I10: 7730 | J10: 1583 | K10: Aug 2023
A11: STMicro | B11: 17290 | C11: 8012 | D11: 2100 | E11: 2980 | F11: 4180 | G11: 11180 | H11: 1204 | I11: 4900 | J11: 4240 | K11: Dec 2023
A12: Infineon | B12: 17400 | C12: 9295 | D12: 1563 | E12: 4050 | F12: 4761 | G12: 12800 | H12: 1089 | I12: 6932 | J12: 3984 | K12: Sep 2023
A14: Sources: AMD/Intel/TXN/NVIDIA/Qualcomm/NXP/Micron → SEC EDGAR 10-K FY2023. TSMC → 20-F (TWD→USD @31.2). STMicro/Infineon → 20-F/Annual Report (EUR→USD @1.065). NVIDIA FY ends Jan-2024 | Qualcomm & Infineon FY end Sep-2023 | Micron FY ends Aug-2023.

Sheet WC_NWC
A1: Working Capital & Net Working Capital Analysis — All values computed via formulas referencing Raw_Data
A2: Company | B2: Total Current Assets ($M) [=Raw_Data!G] | C2: Total Current Liabilities ($M) [=Raw_Data!I] | D2: Working Capital ($M) [=TCA–TCL] | E2: Revenue ($M) [=Raw_Data!B] | F2: WC as % Revenue [=WC÷Rev] | G2: Accounts Receivable ($M) [=Raw_Data!D] | H2: Inventory ($M) [=Raw_Data!E] | I2: Accounts Payable ($M) [=Raw_Data!H] | J2: Operational NWC ($M) [=AR+Inv–AP] | K2: NWC as % Revenue [=NWC÷Rev] | L2: Current Ratio [=TCA÷TCL] (≥1 healthy) | M2: Quick Ratio [=(TCA–Inv)÷TCL] (≥0.8 healthy) | N2: WC/Rev Rank (1=Best) | O2: NWC/Rev Rank (1=Best)
A3: =Raw_Data!A3 | B3: =Raw_Data!G3 | C3: =Raw_Data!I3 | D3: =B3-C3 | E3: =Raw_Data!B3 | F3: =D3/E3 | G3: =Raw_Data!D3 | H3: =Raw_Data!E3 | I3: =Raw_Data!H3 | J3: =G3+H3-I3 | K3: =J3/E3 | L3: =B3/C3 | M3: =(B3-H3)/C3 | N3: =RANK(F3,$F$3:$F$12,1) | O3: =RANK(K3,$K$3:$K$12,1)
A4: =Raw_Data!A4 | B4: =Raw_Data!G4 | C4: =Raw_Data!I4 | D4: =B4-C4 | E4: =Raw_Data!B4 | F4: =D4/E4 | G4: =Raw_Data!D4 | H4: =Raw_Data!E4 | I4: =Raw_Data!H4 | J4: =G4+H4-I4 | K4: =J4/E4 | L4: =B4/C4 | M4: =(B4-H4)/C4 | N4: =RANK(F4,$F$3:$F$12,1) | O4: =RANK(K4,$K$3:$K$12,1)
A5: =Raw_Data!A5 | B5: =Raw_Data!G5 | C5: =Raw_Data!I5 | D5: =B5-C5 | E5: =Raw_Data!B5 | F5: =D5/E5 | G5: =Raw_Data!D5 | H5: =Raw_Data!E5 | I5: =Raw_Data!H5 | J5: =G5+H5-I5 | K5: =J5/E5 | L5: =B5/C5 | M5: =(B5-H5)/C5 | N5: =RANK(F5,$F$3:$F$12,1) | O5: =RANK(K5,$K$3:$K$12,1)
A6: =Raw_Data!A6 | B6: =Raw_Data!G6 | C6: =Raw_Data!I6 | D6: =B6-C6 | E6: =Raw_Data!B6 | F6: =D6/E6 | G6: =Raw_Data!D6 | H6: =Raw_Data!E6 | I6: =Raw_Data!H6 | J6: =G6+H6-I6 | K6: =J6/E6 | L6: =B6/C6 | M6: =(B6-H6)/C6 | N6: =RANK(F6,$F$3:$F$12,1) | O6: =RANK(K6,$K$3:$K$12,1)
A7: =Raw_Data!A7 | B7: =Raw_Data!G7 | C7: =Raw_Data!I7 | D7: =B7-C7 | E7: =Raw_Data!B7 | F7: =D7/E7 | G7: =Raw_Data!D7 | H7: =Raw_Data!E7 | I7: =Raw_Data!H7 | J7: =G7+H7-I7 | K7: =J7/E7 | L7: =B7/C7 | M7: =(B7-H7)/C7 | N7: =RANK(F7,$F$3:$F$12,1) | O7: =RANK(K7,$K$3:$K$12,1)
A8: =Raw_Data!A8 | B8: =Raw_Data!G8 | C8: =Raw_Data!I8 | D8: =B8-C8 | E8: =Raw_Data!B8 | F8: =D8/E8 | G8: =Raw_Data!D8 | H8: =Raw_Data!E8 | I8: =Raw_Data!H8 | J8: =G8+H8-I8 | K8: =J8/E8 | L8: =B8/C8 | M8: =(B8-H8)/C8 | N8: =RANK(F8,$F$3:$F$12,1) | O8: =RANK(K8,$K$3:$K$12,1)
A9: =Raw_Data!A9 | B9: =Raw_Data!G9 | C9: =Raw_Data!I9 | D9: =B9-C9 | E9: =Raw_Data!B9 | F9: =D9/E9 | G9: =Raw_Data!D9 | H9: =Raw_Data!E9 | I9: =Raw_Data!H9 | J9: =G9+H9-I9 | K9: =J9/E9 | L9: =B9/C9 | M9: =(B9-H9)/C9 | N9: =RANK(F9,$F$3:$F$12,1) | O9: =RANK(K9,$K$3:$K$12,1)
A10: =Raw_Data!A10 | B10: =Raw_Data!G10 | C10: =Raw_Data!I10 | D10: =B10-C10 | E10: =Raw_Data!B10 | F10: =D10/E10 | G10: =Raw_Data!D10 | H10: =Raw_Data!E10 | I10: =Raw_Data!H10 | J10: =G10+H10-I10 | K10: =J10/E10 | L10: =B10/C10 | M10: =(B10-H10)/C10 | N10: =RANK(F10,$F$3:$F$12,1) | O10: =RANK(K10,$K$3:$K$12,1)
A11: =Raw_Data!A11 | B11: =Raw_Data!G11 | C11: =Raw_Data!I11 | D11: =B11-C11 | E11: =Raw_Data!B11 | F11: =D11/E11 | G11: =Raw_Data!D11 | H11: =Raw_Data!E11 | I11: =Raw_Data!H11 | J11: =G11+H11-I11 | K11: =J11/E11 | L11: =B11/C11 | M11: =(B11-H11)/C11 | N11: =RANK(F11,$F$3:$F$12,1) | O11: =RANK(K11,$K$3:$K$12,1)
A12: =Raw_Data!A12 | B12: =Raw_Data!G12 | C12: =Raw_Data!I12 | D12: =B12-C12 | E12: =Raw_Data!B12 | F12: =D12/E12 | G12: =Raw_Data!D12 | H12: =Raw_Data!E12 | I12: =Raw_Data!H12 | J12: =G12+H12-I12 | K12: =J12/E12 | L12: =B12/C12 | M12: =(B12-H12)/C12 | N12: =RANK(F12,$F$3:$F$12,1) | O12: =RANK(K12,$K$3:$K$12,1)
A14: Best-in-Class WC/Rev → | F14: =MIN(F3:F12)
A15: Best-in-Class NWC/Rev → | K15: =MIN(K3:K12)
A16: Peer-Avg Current Ratio → | L16: =AVERAGE(L3:L12)
A17: Peer-Avg Quick Ratio → | M17: =AVERAGE(M3:M12)
A19: Current Ratio=TCA÷TCL | Quick Ratio=(TCA–Inv)÷TCL | Operational NWC=AR+Inv–AP (excludes cash/short-term debt).

Sheet Efficiency_Metrics
A1: Efficiency Metrics: DSO | AR Turns | DIO | Inv Turns | DPO | CCC | CRR — All formulas reference Raw_Data
A2: Company | B2: Revenue ($M) | C2: COGS ($M) | D2: AR ($M) | E2: Inventory ($M) | F2: AP ($M) | G2: Op. Cash Flow ($M) | H2: DSO (days) [=AR÷Rev×365] (↓ better) | I2: AR Turns [=Rev÷AR] (↑ better) | J2: DIO (days) [=Inv÷COGS×365] (↓ better) | K2: Inv Turns [=COGS÷Inv] (↑ better) | L2: DPO (days) [=AP÷COGS×365] (↑ better) | M2: CCC (days) [=DSO+DIO–DPO] (↓ better) | N2: CRR [=OCF÷Rev] (↑ better) | O2: DSO Rank (1=Best) | P2: DIO Rank (1=Best) | Q2: DPO Rank (1=Best) | R2: CCC Rank (1=Best)
A3: =Raw_Data!A3 | B3: =Raw_Data!B3 | C3: =Raw_Data!C3 | D3: =Raw_Data!D3 | E3: =Raw_Data!E3 | F3: =Raw_Data!H3 | G3: =Raw_Data!J3 | H3: =D3/B3*365 | I3: =B3/D3 | J3: =E3/C3*365 | K3: =C3/E3 | L3: =F3/C3*365 | M3: =H3+J3-L3 | N3: =G3/B3 | O3: =RANK(H3,$H$3:$H$12,1) | P3: =RANK(J3,$J$3:$J$12,1) | Q3: =RANK(L3,$L$3:$L$12,0) | R3: =RANK(M3,$M$3:$M$12,1)
A4: =Raw_Data!A4 | B4: =Raw_Data!B4 | C4: =Raw_Data!C4 | D4: =Raw_Data!D4 | E4: =Raw_Data!E4 | F4: =Raw_Data!H4 | G4: =Raw_Data!J4 | H4: =D4/B4*365 | I4: =B4/D4 | J4: =E4/C4*365 | K4: =C4/E4 | L4: =F4/C4*365 | M4: =H4+J4-L4 | N4: =G4/B4 | O4: =RANK(H4,$H$3:$H$12,1) | P4: =RANK(J4,$J$3:$J$12,1) | Q4: =RANK(L4,$L$3:$L$12,0) | R4: =RANK(M4,$M$3:$M$12,1)
A5: =Raw_Data!A5 | B5: =Raw_Data!B5 | C5: =Raw_Data!C5 | D5: =Raw_Data!D5 | E5: =Raw_Data!E5 | F5: =Raw_Data!H5 | G5: =Raw_Data!J5 | H5: =D5/B5*365 | I5: =B5/D5 | J5: =E5/C5*365 | K5: =C5/E5 | L5: =F5/C5*365 | M5: =H5+J5-L5 | N5: =G5/B5 | O5: =RANK(H5,$H$3:$H$12,1) | P5: =RANK(J5,$J$3:$J$12,1) | Q5: =RANK(L5,$L$3:$L$12,0) | R5: =RANK(M5,$M$3:$M$12,1)
A6: =Raw_Data!A6 | B6: =Raw_Data!B6 | C6: =Raw_Data!C6 | D6: =Raw_Data!D6 | E6: =Raw_Data!E6 | F6: =Raw_Data!H6 | G6: =Raw_Data!J6 | H6: =D6/B6*365 | I6: =B6/D6 | J6: =E6/C6*365 | K6: =C6/E6 | L6: =F6/C6*365 | M6: =H6+J6-L6 | N6: =G6/B6 | O6: =RANK(H6,$H$3:$H$12,1) | P6: =RANK(J6,$J$3:$J$12,1) | Q6: =RANK(L6,$L$3:$L$12,0) | R6: =RANK(M6,$M$3:$M$12,1)
A7: =Raw_Data!A7 | B7: =Raw_Data!B7 | C7: =Raw_Data!C7 | D7: =Raw_Data!D7 | E7: =Raw_Data!E7 | F7: =Raw_Data!H7 | G7: =Raw_Data!J7 | H7: =D7/B7*365 | I7: =B7/D7 | J7: =E7/C7*365 | K7: =C7/E7 | L7: =F7/C7*365 | M7: =H7+J7-L7 | N7: =G7/B7 | O7: =RANK(H7,$H$3:$H$12,1) | P7: =RANK(J7,$J$3:$J$12,1) | Q7: =RANK(L7,$L$3:$L$12,0) | R7: =RANK(M7,$M$3:$M$12,1)
A8: =Raw_Data!A8 | B8: =Raw_Data!B8 | C8: =Raw_Data!C8 | D8: =Raw_Data!D8 | E8: =Raw_Data!E8 | F8: =Raw_Data!H8 | G8: =Raw_Data!J8 | H8: =D8/B8*365 | I8: =B8/D8 | J8: =E8/C8*365 | K8: =C8/E8 | L8: =F8/C8*365 | M8: =H8+J8-L8 | N8: =G8/B8 | O8: =RANK(H8,$H$3:$H$12,1) | P8: =RANK(J8,$J$3:$J$12,1) | Q8: =RANK(L8,$L$3:$L$12,0) | R8: =RANK(M8,$M$3:$M$12,1)
A9: =Raw_Data!A9 | B9: =Raw_Data!B9 | C9: =Raw_Data!C9 | D9: =Raw_Data!D9 | E9: =Raw_Data!E9 | F9: =Raw_Data!H9 | G9: =Raw_Data!J9 | H9: =D9/B9*365 | I9: =B9/D9 | J9: =E9/C9*365 | K9: =C9/E9 | L9: =F9/C9*365 | M9: =H9+J9-L9 | N9: =G9/B9 | O9: =RANK(H9,$H$3:$H$12,1) | P9: =RANK(J9,$J$3:$J$12,1) | Q9: =RANK(L9,$L$3:$L$12,0) | R9: =RANK(M9,$M$3:$M$12,1)
A10: =Raw_Data!A10 | B10: =Raw_Data!B10 | C10: =Raw_Data!C10 | D10: =Raw_Data!D10 | E10: =Raw_Data!E10 | F10: =Raw_Data!H10 | G10: =Raw_Data!J10 | H10: =D10/B10*365 | I10: =B10/D10 | J10: =E10/C10*365 | K10: =C10/E10 | L10: =F10/C10*365 | M10: =H10+J10-L10 | N10: =G10/B10 | O10: =RANK(H10,$H$3:$H$12,1) | P10: =RANK(J10,$J$3:$J$12,1) | Q10: =RANK(L10,$L$3:$L$12,0) | R10: =RANK(M10,$M$3:$M$12,1)
A11: =Raw_Data!A11 | B11: =Raw_Data!B11 | C11: =Raw_Data!C11 | D11: =Raw_Data!D11 | E11: =Raw_Data!E11 | F11: =Raw_Data!H11 | G11: =Raw_Data!J11 | H11: =D11/B11*365 | I11: =B11/D11 | J11: =E11/C11*365 | K11: =C11/E11 | L11: =F11/C11*365 | M11: =H11+J11-L11 | N11: =G11/B11 | O11: =RANK(H11,$H$3:$H$12,1) | P11: =RANK(J11,$J$3:$J$12,1) | Q11: =RANK(L11,$L$3:$L$12,0) | R11: =RANK(M11,$M$3:$M$12,1)
A12: =Raw_Data!A12 | B12: =Raw_Data!B12 | C12: =Raw_Data!C12 | D12: =Raw_Data!D12 | E12: =Raw_Data!E12 | F12: =Raw_Data!H12 | G12: =Raw_Data!J12 | H12: =D12/B12*365 | I12: =B12/D12 | J12: =E12/C12*365 | K12: =C12/E12 | L12: =F12/C12*365 | M12: =H12+J12-L12 | N12: =G12/B12 | O12: =RANK(H12,$H$3:$H$12,1) | P12: =RANK(J12,$J$3:$J$12,1) | Q12: =RANK(L12,$L$3:$L$12,0) | R12: =RANK(M12,$M$3:$M$12,1)
A14: Best DSO (Min): | H14: =MIN(H3:H12)
A15: Best AR Turns (Max): | I15: =MAX(I3:I12)
A16: Best DIO (Min): | J16: =MIN(J3:J12)
A17: Best Inv Turns (Max): | K17: =MAX(K3:K12)
A18: Best DPO (Max): | L18: =MAX(L3:L12)
A19: Best CCC (Min): | M19: =MIN(M3:M12)
A20: Best CRR (Max): | N20: =MAX(N3:N12)
A21: DPO Rank: higher DPO = better (supplier financing). CCC Rank: lower CCC = better. Inv Turns = COGS÷Inventory. AR Turns = Revenue÷AR. CRR = OCF÷Revenue.

Sheet Scoring_Ranking
A1: Overall Scoring Model — Rank-Sum (6 Metrics | Equal Weight | Lower Total Score = Better Overall)
A2: Company | B2: WC/Rev Rank [WC_NWC!N] | C2: NWC/Rev Rank [WC_NWC!O] | D2: DSO Rank [Eff!P] | E2: DIO Rank [Eff!Q] | F2: DPO Rank [Eff!R] | G2: CCC Rank [Eff!S] | H2: Total Score [=SUM(B:G)] Lower=Better | I2: Overall Rank [=RANK(…)] | J2: Quartile [=IF(rank≤2,Q1,…)]
A3: =Raw_Data!A3 | B3: =WC_NWC!N3 | C3: =WC_NWC!O3 | D3: =Efficiency_Metrics!P3 | E3: =Efficiency_Metrics!Q3 | F3: =Efficiency_Metrics!R3 | G3: =Efficiency_Metrics!S3 | H3: =SUM(B3:G3) | I3: =RANK(H3,$H$3:$H$12,1) | J3: =IF(I3<=2,"Q1",IF(I3<=5,"Q2",IF(I3<=7,"Q3","Q4")))
A4: =Raw_Data!A4 | B4: =WC_NWC!N4 | C4: =WC_NWC!O4 | D4: =Efficiency_Metrics!P4 | E4: =Efficiency_Metrics!Q4 | F4: =Efficiency_Metrics!R4 | G4: =Efficiency_Metrics!S4 | H4: =SUM(B4:G4) | I4: =RANK(H4,$H$3:$H$12,1) | J4: =IF(I4<=2,"Q1",IF(I4<=5,"Q2",IF(I4<=7,"Q3","Q4")))
A5: =Raw_Data!A5 | B5: =WC_NWC!N5 | C5: =WC_NWC!O5 | D5: =Efficiency_Metrics!P5 | E5: =Efficiency_Metrics!Q5 | F5: =Efficiency_Metrics!R5 | G5: =Efficiency_Metrics!S5 | H5: =SUM(B5:G5) | I5: =RANK(H5,$H$3:$H$12,1) | J5: =IF(I5<=2,"Q1",IF(I5<=5,"Q2",IF(I5<=7,"Q3","Q4")))
A6: =Raw_Data!A6 | B6: =WC_NWC!N6 | C6: =WC_NWC!O6 | D6: =Efficiency_Metrics!P6 | E6: =Efficiency_Metrics!Q6 | F6: =Efficiency_Metrics!R6 | G6: =Efficiency_Metrics!S6 | H6: =SUM(B6:G6) | I6: =RANK(H6,$H$3:$H$12,1) | J6: =IF(I6<=2,"Q1",IF(I6<=5,"Q2",IF(I6<=7,"Q3","Q4")))
A7: =Raw_Data!A7 | B7: =WC_NWC!N7 | C7: =WC_NWC!O7 | D7: =Efficiency_Metrics!P7 | E7: =Efficiency_Metrics!Q7 | F7: =Efficiency_Metrics!R7 | G7: =Efficiency_Metrics!S7 | H7: =SUM(B7:G7) | I7: =RANK(H7,$H$3:$H$12,1) | J7: =IF(I7<=2,"Q1",IF(I7<=5,"Q2",IF(I7<=7,"Q3","Q4")))
A8: =Raw_Data!A8 | B8: =WC_NWC!N8 | C8: =WC_NWC!O8 | D8: =Efficiency_Metrics!P8 | E8: =Efficiency_Metrics!Q8 | F8: =Efficiency_Metrics!R8 | G8: =Efficiency_Metrics!S8 | H8: =SUM(B8:G8) | I8: =RANK(H8,$H$3:$H$12,1) | J8: =IF(I8<=2,"Q1",IF(I8<=5,"Q2",IF(I8<=7,"Q3","Q4")))
A9: =Raw_Data!A9 | B9: =WC_NWC!N9 | C9: =WC_NWC!O9 | D9: =Efficiency_Metrics!P9 | E9: =Efficiency_Metrics!Q9 | F9: =Efficiency_Metrics!R9 | G9: =Efficiency_Metrics!S9 | H9: =SUM(B9:G9) | I9: =RANK(H9,$H$3:$H$12,1) | J9: =IF(I9<=2,"Q1",IF(I9<=5,"Q2",IF(I9<=7,"Q3","Q4")))
A10: =Raw_Data!A10 | B10: =WC_NWC!N10 | C10: =WC_NWC!O10 | D10: =Efficiency_Metrics!P10 | E10: =Efficiency_Metrics!Q10 | F10: =Efficiency_Metrics!R10 | G10: =Efficiency_Metrics!S10 | H10: =SUM(B10:G10) | I10: =RANK(H10,$H$3:$H$12,1) | J10: =IF(I10<=2,"Q1",IF(I10<=5,"Q2",IF(I10<=7,"Q3","Q4")))
A11: =Raw_Data!A11 | B11: =WC_NWC!N11 | C11: =WC_NWC!O11 | D11: =Efficiency_Metrics!P11 | E11: =Efficiency_Metrics!Q11 | F11: =Efficiency_Metrics!R11 | G11: =Efficiency_Metrics!S11 | H11: =SUM(B11:G11) | I11: =RANK(H11,$H$3:$H$12,1) | J11: =IF(I11<=2,"Q1",IF(I11<=5,"Q2",IF(I11<=7,"Q3","Q4")))
A12: =Raw_Data!A12 | B12: =WC_NWC!N12 | C12: =WC_NWC!O12 | D12: =Efficiency_Metrics!P12 | E12: =Efficiency_Metrics!Q12 | F12: =Efficiency_Metrics!R12 | G12: =Efficiency_Metrics!S12 | H12: =SUM(B12:G12) | I12: =RANK(H12,$H$3:$H$12,1) | J12: =IF(I12<=2,"Q1",IF(I12<=5,"Q2",IF(I12<=7,"Q3","Q4")))
A14: AR Turns & Inv Turns excluded (inverse of DSO/DIO → would double-count). 6 metrics: WC/Rev, NWC/Rev, DSO, DIO, DPO, CCC — equal weight. DPO rank flipped so higher DPO = rank 1 (benefit).

Sheet Benchmark_Analysis
A1: Gap-to-Best-Practice Benchmark Analysis — DSO | DIO | DPO | CCC | NWC/Rev | CRR
A2: Company | B2: Overall Rank | C2: Quartile | D2: DSO (days) | E2: Best DSO [=MIN] | F2: DSO Gap [Act–Best] +ve=worse | G2: DIO (days) | H2: Best DIO [=MIN] | I2: DIO Gap [Act–Best] +ve=worse | J2: DPO (days) | K2: Best DPO [=MAX] | L2: DPO Gap [Best–Act] +ve=worse | M2: CCC (days) | N2: Best CCC [=MIN] | O2: CCC Gap [Act–Best] +ve=worse | P2: NWC/Rev (%) | Q2: Best NWC/Rev [=MIN] | R2: NWC Gap [Act–Best] +ve=worse
A3: =Raw_Data!A3 | B3: =Scoring_Ranking!I3 | C3: =Scoring_Ranking!J3 | D3: =Efficiency_Metrics!H3 | E3: =MIN(Efficiency_Metrics!$H$3:Efficiency_Metrics!$H$12) | F3: =D3-E3 | G3: =Efficiency_Metrics!J3 | H3: =MIN(Efficiency_Metrics!$J$3:Efficiency_Metrics!$J$12) | I3: =G3-H3 | J3: =Efficiency_Metrics!L3 | K3: =MAX(Efficiency_Metrics!$L$3:Efficiency_Metrics!$L$12) | L3: =K3-J3 | M3: =Efficiency_Metrics!M3 | N3: =MIN(Efficiency_Metrics!$M$3:Efficiency_Metrics!$M$12) | O3: =M3-N3 | P3: =WC_NWC!K3 | Q3: =MIN(WC_NWC!$K$3:WC_NWC!$K$12) | R3: =P3-Q3
A4: =Raw_Data!A4 | B4: =Scoring_Ranking!I4 | C4: =Scoring_Ranking!J4 | D4: =Efficiency_Metrics!H4 | E4: =MIN(Efficiency_Metrics!$H$3:Efficiency_Metrics!$H$12) | F4: =D4-E4 | G4: =Efficiency_Metrics!J4 | H4: =MIN(Efficiency_Metrics!$J$3:Efficiency_Metrics!$J$12) | I4: =G4-H4 | J4: =Efficiency_Metrics!L4 | K4: =MAX(Efficiency_Metrics!$L$3:Efficiency_Metrics!$L$12) | L4: =K4-J4 | M4: =Efficiency_Metrics!M4 | N4: =MIN(Efficiency_Metrics!$M$3:Efficiency_Metrics!$M$12) | O4: =M4-N4 | P4: =WC_NWC!K4 | Q4: =MIN(WC_NWC!$K$3:WC_NWC!$K$12) | R4: =P4-Q4
A5: =Raw_Data!A5 | B5: =Scoring_Ranking!I5 | C5: =Scoring_Ranking!J5 | D5: =Efficiency_Metrics!H5 | E5: =MIN(Efficiency_Metrics!$H$3:Efficiency_Metrics!$H$12) | F5: =D5-E5 | G5: =Efficiency_Metrics!J5 | H5: =MIN(Efficiency_Metrics!$J$3:Efficiency_Metrics!$J$12) | I5: =G5-H5 | J5: =Efficiency_Metrics!L5 | K5: =MAX(Efficiency_Metrics!$L$3:Efficiency_Metrics!$L$12) | L5: =K5-J5 | M5: =Efficiency_Metrics!M5 | N5: =MIN(Efficiency_Metrics!$M$3:Efficiency_Metrics!$M$12) | O5: =M5-N5 | P5: =WC_NWC!K5 | Q5: =MIN(WC_NWC!$K$3:WC_NWC!$K$12) | R5: =P5-Q5
A6: =Raw_Data!A6 | B6: =Scoring_Ranking!I6 | C6: =Scoring_Ranking!J6 | D6: =Efficiency_Metrics!H6 | E6: =MIN(Efficiency_Metrics!$H$3:Efficiency_Metrics!$H$12) | F6: =D6-E6 | G6: =Efficiency_Metrics!J6 | H6: =MIN(Efficiency_Metrics!$J$3:Efficiency_Metrics!$J$12) | I6: =G6-H6 | J6: =Efficiency_Metrics!L6 | K6: =MAX(Efficiency_Metrics!$L$3:Efficiency_Metrics!$L$12) | L6: =K6-J6 | M6: =Efficiency_Metrics!M6 | N6: =MIN(Efficiency_Metrics!$M$3:Efficiency_Metrics!$M$12) | O6: =M6-N6 | P6: =WC_NWC!K6 | Q6: =MIN(WC_NWC!$K$3:WC_NWC!$K$12) | R6: =P6-Q6
A7: =Raw_Data!A7 | B7: =Scoring_Ranking!I7 | C7: =Scoring_Ranking!J7 | D7: =Efficiency_Metrics!H7 | E7: =MIN(Efficiency_Metrics!$H$3:Efficiency_Metrics!$H$12) | F7: =D7-E7 | G7: =Efficiency_Metrics!J7 | H7: =MIN(Efficiency_Metrics!$J$3:Efficiency_Metrics!$J$12) | I7: =G7-H7 | J7: =Efficiency_Metrics!L7 | K7: =MAX(Efficiency_Metrics!$L$3:Efficiency_Metrics!$L$12) | L7: =K7-J7 | M7: =Efficiency_Metrics!M7 | N7: =MIN(Efficiency_Metrics!$M$3:Efficiency_Metrics!$M$12) | O7: =M7-N7 | P7: =WC_NWC!K7 | Q7: =MIN(WC_NWC!$K$3:WC_NWC!$K$12) | R7: =P7-Q7
A8: =Raw_Data!A8 | B8: =Scoring_Ranking!I8 | C8: =Scoring_Ranking!J8 | D8: =Efficiency_Metrics!H8 | E8: =MIN(Efficiency_Metrics!$H$3:Efficiency_Metrics!$H$12) | F8: =D8-E8 | G8: =Efficiency_Metrics!J8 | H8: =MIN(Efficiency_Metrics!$J$3:Efficiency_Metrics!$J$12) | I8: =G8-H8 | J8: =Efficiency_Metrics!L8 | K8: =MAX(Efficiency_Metrics!$L$3:Efficiency_Metrics!$L$12) | L8: =K8-J8 | M8: =Efficiency_Metrics!M8 | N8: =MIN(Efficiency_Metrics!$M$3:Efficiency_Metrics!$M$12) | O8: =M8-N8 | P8: =WC_NWC!K8 | Q8: =MIN(WC_NWC!$K$3:WC_NWC!$K$12) | R8: =P8-Q8
A9: =Raw_Data!A9 | B9: =Scoring_Ranking!I9 | C9: =Scoring_Ranking!J9 | D9: =Efficiency_Metrics!H9 | E9: =MIN(Efficiency_Metrics!$H$3:Efficiency_Metrics!$H$12) | F9: =D9-E9 | G9: =Efficiency_Metrics!J9 | H9: =MIN(Efficiency_Metrics!$J$3:Efficiency_Metrics!$J$12) | I9: =G9-H9 | J9: =Efficiency_Metrics!L9 | K9: =MAX(Efficiency_Metrics!$L$3:Efficiency_Metrics!$L$12) | L9: =K9-J9 | M9: =Efficiency_Metrics!M9 | N9: =MIN(Efficiency_Metrics!$M$3:Efficiency_Metrics!$M$12) | O9: =M9-N9 | P9: =WC_NWC!K9 | Q9: =MIN(WC_NWC!$K$3:WC_NWC!$K$12) | R9: =P9-Q9
A10: =Raw_Data!A10 | B10: =Scoring_Ranking!I10 | C10: =Scoring_Ranking!J10 | D10: =Efficiency_Metrics!H10 | E10: =MIN(Efficiency_Metrics!$H$3:Efficiency_Metrics!$H$12) | F10: =D10-E10 | G10: =Efficiency_Metrics!J10 | H10: =MIN(Efficiency_Metrics!$J$3:Efficiency_Metrics!$J$12) | I10: =G10-H10 | J10: =Efficiency_Metrics!L10 | K10: =MAX(Efficiency_Metrics!$L$3:Efficiency_Metrics!$L$12) | L10: =K10-J10 | M10: =Efficiency_Metrics!M10 | N10: =MIN(Efficiency_Metrics!$M$3:Efficiency_Metrics!$M$12) | O10: =M10-N10 | P10: =WC_NWC!K10 | Q10: =MIN(WC_NWC!$K$3:WC_NWC!$K$12) | R10: =P10-Q10
A11: =Raw_Data!A11 | B11: =Scoring_Ranking!I11 | C11: =Scoring_Ranking!J11 | D11: =Efficiency_Metrics!H11 | E11: =MIN(Efficiency_Metrics!$H$3:Efficiency_Metrics!$H$12) | F11: =D11-E11 | G11: =Efficiency_Metrics!J11 | H11: =MIN(Efficiency_Metrics!$J$3:Efficiency_Metrics!$J$12) | I11: =G11-H11 | J11: =Efficiency_Metrics!L11 | K11: =MAX(Efficiency_Metrics!$L$3:Efficiency_Metrics!$L$12) | L11: =K11-J11 | M11: =Efficiency_Metrics!M11 | N11: =MIN(Efficiency_Metrics!$M$3:Efficiency_Metrics!$M$12) | O11: =M11-N11 | P11: =WC_NWC!K11 | Q11: =MIN(WC_NWC!$K$3:WC_NWC!$K$12) | R11: =P11-Q11
A12: =Raw_Data!A12 | B12: =Scoring_Ranking!I12 | C12: =Scoring_Ranking!J12 | D12: =Efficiency_Metrics!H12 | E12: =MIN(Efficiency_Metrics!$H$3:Efficiency_Metrics!$H$12) | F12: =D12-E12 | G12: =Efficiency_Metrics!J12 | H12: =MIN(Efficiency_Metrics!$J$3:Efficiency_Metrics!$J$12) | I12: =G12-H12 | J12: =Efficiency_Metrics!L12 | K12: =MAX(Efficiency_Metrics!$L$3:Efficiency_Metrics!$L$12) | L12: =K12-J12 | M12: =Efficiency_Metrics!M12 | N12: =MIN(Efficiency_Metrics!$M$3:Efficiency_Metrics!$M$12) | O12: =M12-N12 | P12: =WC_NWC!K12 | Q12: =MIN(WC_NWC!$K$3:WC_NWC!$K$12) | R12: =P12-Q12
A14: DSO/DIO/CCC gap: positive = company is WORSE than best practice. DPO gap: positive = company is paying suppliers FASTER than best practice (cash disadvantage). All best-practice values are dynamic MIN/MAX across the peer group.

Sheet Cash_Release
A1: Cash Release Potential — AR | Inventory | AP — All formulas dynamic (Target = 2nd-Best Peer)
A2: Company | B2: Quartile | C2: Revenue ($M) | D2: COGS ($M) | E2: Current AR ($M) | F2: Current DSO (days) | G2: Target DSO [=SMALL(…,2)] | H2: Target AR [=Rev÷365×TgtDSO] | I2: AR Cash Release [=MAX(AR–TgtAR,0)] | J2: Current Inv ($M) | K2: Current DIO (days) | L2: Target DIO [=SMALL(…,2)] | M2: Target Inv [=COGS÷365×TgtDIO] | N2: Inv Cash Release [=MAX(Inv–TgtInv,0)] | O2: Current AP ($M) | P2: Current DPO (days) | Q2: Target DPO [=LARGE(…,2)] | R2: Target AP [=COGS÷365×TgtDPO] | S2: AP Cash Release [=MAX(TgtAP–AP,0)] (extend terms) | T2: TOTAL Cash Release [=AR+Inv+AP] ($M)
A3: =Raw_Data!A3 | B3: =Scoring_Ranking!J3 | C3: =Raw_Data!B3 | D3: =Raw_Data!C3 | E3: =Raw_Data!D3 | F3: =Efficiency_Metrics!H3 | G3: =SMALL(Efficiency_Metrics!$H$3:Efficiency_Metrics!$H$12,2) | H3: =C3/365*G3 | I3: =MAX(E3-H3,0) | J3: =Raw_Data!E3 | K3: =Efficiency_Metrics!J3 | L3: =SMALL(Efficiency_Metrics!$J$3:Efficiency_Metrics!$J$12,2) | M3: =D3/365*L3 | N3: =MAX(J3-M3,0) | O3: =Raw_Data!H3 | P3: =Efficiency_Metrics!L3 | Q3: =LARGE(Efficiency_Metrics!$L$3:Efficiency_Metrics!$L$12,2) | R3: =D3/365*Q3 | S3: =MAX(R3-O3,0) | T3: =I3+N3+S3
A4: =Raw_Data!A4 | B4: =Scoring_Ranking!J4 | C4: =Raw_Data!B4 | D4: =Raw_Data!C4 | E4: =Raw_Data!D4 | F4: =Efficiency_Metrics!H4 | G4: =SMALL(Efficiency_Metrics!$H$3:Efficiency_Metrics!$H$12,2) | H4: =C4/365*G4 | I4: =MAX(E4-H4,0) | J4: =Raw_Data!E4 | K4: =Efficiency_Metrics!J4 | L4: =SMALL(Efficiency_Metrics!$J$3:Efficiency_Metrics!$J$12,2) | M4: =D4/365*L4 | N4: =MAX(J4-M4,0) | O4: =Raw_Data!H4 | P4: =Efficiency_Metrics!L4 | Q4: =LARGE(Efficiency_Metrics!$L$3:Efficiency_Metrics!$L$12,2) | R4: =D4/365*Q4 | S4: =MAX(R4-O4,0) | T4: =I4+N4+S4
A5: =Raw_Data!A5 | B5: =Scoring_Ranking!J5 | C5: =Raw_Data!B5 | D5: =Raw_Data!C5 | E5: =Raw_Data!D5 | F5: =Efficiency_Metrics!H5 | G5: =SMALL(Efficiency_Metrics!$H$3:Efficiency_Metrics!$H$12,2) | H5: =C5/365*G5 | I5: =MAX(E5-H5,0) | J5: =Raw_Data!E5 | K5: =Efficiency_Metrics!J5 | L5: =SMALL(Efficiency_Metrics!$J$3:Efficiency_Metrics!$J$12,2) | M5: =D5/365*L5 | N5: =MAX(J5-M5,0) | O5: =Raw_Data!H5 | P5: =Efficiency_Metrics!L5 | Q5: =LARGE(Efficiency_Metrics!$L$3:Efficiency_Metrics!$L$12,2) | R5: =D5/365*Q5 | S5: =MAX(R5-O5,0) | T5: =I5+N5+S5
A6: =Raw_Data!A6 | B6: =Scoring_Ranking!J6 | C6: =Raw_Data!B6 | D6: =Raw_Data!C6 | E6: =Raw_Data!D6 | F6: =Efficiency_Metrics!H6 | G6: =SMALL(Efficiency_Metrics!$H$3:Efficiency_Metrics!$H$12,2) | H6: =C6/365*G6 | I6: =MAX(E6-H6,0) | J6: =Raw_Data!E6 | K6: =Efficiency_Metrics!J6 | L6: =SMALL(Efficiency_Metrics!$J$3:Efficiency_Metrics!$J$12,2) | M6: =D6/365*L6 | N6: =MAX(J6-M6,0) | O6: =Raw_Data!H6 | P6: =Efficiency_Metrics!L6 | Q6: =LARGE(Efficiency_Metrics!$L$3:Efficiency_Metrics!$L$12,2) | R6: =D6/365*Q6 | S6: =MAX(R6-O6,0) | T6: =I6+N6+S6
A7: =Raw_Data!A7 | B7: =Scoring_Ranking!J7 | C7: =Raw_Data!B7 | D7: =Raw_Data!C7 | E7: =Raw_Data!D7 | F7: =Efficiency_Metrics!H7 | G7: =SMALL(Efficiency_Metrics!$H$3:Efficiency_Metrics!$H$12,2) | H7: =C7/365*G7 | I7: =MAX(E7-H7,0) | J7: =Raw_Data!E7 | K7: =Efficiency_Metrics!J7 | L7: =SMALL(Efficiency_Metrics!$J$3:Efficiency_Metrics!$J$12,2) | M7: =D7/365*L7 | N7: =MAX(J7-M7,0) | O7: =Raw_Data!H7 | P7: =Efficiency_Metrics!L7 | Q7: =LARGE(Efficiency_Metrics!$L$3:Efficiency_Metrics!$L$12,2) | R7: =D7/365*Q7 | S7: =MAX(R7-O7,0) | T7: =I7+N7+S7
A8: =Raw_Data!A8 | B8: =Scoring_Ranking!J8 | C8: =Raw_Data!B8 | D8: =Raw_Data!C8 | E8: =Raw_Data!D8 | F8: =Efficiency_Metrics!H8 | G8: =SMALL(Efficiency_Metrics!$H$3:Efficiency_Metrics!$H$12,2) | H8: =C8/365*G8 | I8: =MAX(E8-H8,0) | J8: =Raw_Data!E8 | K8: =Efficiency_Metrics!J8 | L8: =SMALL(Efficiency_Metrics!$J$3:Efficiency_Metrics!$J$12,2) | M8: =D8/365*L8 | N8: =MAX(J8-M8,0) | O8: =Raw_Data!H8 | P8: =Efficiency_Metrics!L8 | Q8: =LARGE(Efficiency_Metrics!$L$3:Efficiency_Metrics!$L$12,2) | R8: =D8/365*Q8 | S8: =MAX(R8-O8,0) | T8: =I8+N8+S8
A9: =Raw_Data!A9 | B9: =Scoring_Ranking!J9 | C9: =Raw_Data!B9 | D9: =Raw_Data!C9 | E9: =Raw_Data!D9 | F9: =Efficiency_Metrics!H9 | G9: =SMALL(Efficiency_Metrics!$H$3:Efficiency_Metrics!$H$12,2) | H9: =C9/365*G9 | I9: =MAX(E9-H9,0) | J9: =Raw_Data!E9 | K9: =Efficiency_Metrics!J9 | L9: =SMALL(Efficiency_Metrics!$J$3:Efficiency_Metrics!$J$12,2) | M9: =D9/365*L9 | N9: =MAX(J9-M9,0) | O9: =Raw_Data!H9 | P9: =Efficiency_Metrics!L9 | Q9: =LARGE(Efficiency_Metrics!$L$3:Efficiency_Metrics!$L$12,2) | R9: =D9/365*Q9 | S9: =MAX(R9-O9,0) | T9: =I9+N9+S9
A10: =Raw_Data!A10 | B10: =Scoring_Ranking!J10 | C10: =Raw_Data!B10 | D10: =Raw_Data!C10 | E10: =Raw_Data!D10 | F10: =Efficiency_Metrics!H10 | G10: =SMALL(Efficiency_Metrics!$H$3:Efficiency_Metrics!$H$12,2) | H10: =C10/365*G10 | I10: =MAX(E10-H10,0) | J10: =Raw_Data!E10 | K10: =Efficiency_Metrics!J10 | L10: =SMALL(Efficiency_Metrics!$J$3:Efficiency_Metrics!$J$12,2) | M10: =D10/365*L10 | N10: =MAX(J10-M10,0) | O10: =Raw_Data!H10 | P10: =Efficiency_Metrics!L10 | Q10: =LARGE(Efficiency_Metrics!$L$3:Efficiency_Metrics!$L$12,2) | R10: =D10/365*Q10 | S10: =MAX(R10-O10,0) | T10: =I10+N10+S10
A11: =Raw_Data!A11 | B11: =Scoring_Ranking!J11 | C11: =Raw_Data!B11 | D11: =Raw_Data!C11 | E11: =Raw_Data!D11 | F11: =Efficiency_Metrics!H11 | G11: =SMALL(Efficiency_Metrics!$H$3:Efficiency_Metrics!$H$12,2) | H11: =C11/365*G11 | I11: =MAX(E11-H11,0) | J11: =Raw_Data!E11 | K11: =Efficiency_Metrics!J11 | L11: =SMALL(Efficiency_Metrics!$J$3:Efficiency_Metrics!$J$12,2) | M11: =D11/365*L11 | N11: =MAX(J11-M11,0) | O11: =Raw_Data!H11 | P11: =Efficiency_Metrics!L11 | Q11: =LARGE(Efficiency_Metrics!$L$3:Efficiency_Metrics!$L$12,2) | R11: =D11/365*Q11 | S11: =MAX(R11-O11,0) | T11: =I11+N11+S11
A12: =Raw_Data!A12 | B12: =Scoring_Ranking!J12 | C12: =Raw_Data!B12 | D12: =Raw_Data!C12 | E12: =Raw_Data!D12 | F12: =Efficiency_Metrics!H12 | G12: =SMALL(Efficiency_Metrics!$H$3:Efficiency_Metrics!$H$12,2) | H12: =C12/365*G12 | I12: =MAX(E12-H12,0) | J12: =Raw_Data!E12 | K12: =Efficiency_Metrics!J12 | L12: =SMALL(Efficiency_Metrics!$J$3:Efficiency_Metrics!$J$12,2) | M12: =D12/365*L12 | N12: =MAX(J12-M12,0) | O12: =Raw_Data!H12 | P12: =Efficiency_Metrics!L12 | Q12: =LARGE(Efficiency_Metrics!$L$3:Efficiency_Metrics!$L$12,2) | R12: =D12/365*Q12 | S12: =MAX(R12-O12,0) | T12: =I12+N12+S12
A14: TOTAL All 10 Companies (MAX(…,0) ensures below-target contributes $0): | I14: =SUM(I3:I12) | N14: =SUM(N3:N12) | S14: =SUM(S3:S12) | T14: =SUM(T3:T12)
A15: =CONCATENATE("TOTAL Q3+Q4 Companies (",COUNTIF(B3:B12,"Q3")+COUNTIF(B3:B12,"Q4")," cos): AR | Inv | AP | Combined") | I15: =SUMIF(B3:B12,"Q3",I3:I12)+SUMIF(B3:B12,"Q4",I3:I12) | N15: =SUMIF(B3:B12,"Q3",N3:N12)+SUMIF(B3:B12,"Q4",N3:N12) | S15: =SUMIF(B3:B12,"Q3",S3:S12)+SUMIF(B3:B12,"Q4",S3:S12) | T15: =SUMIF(B3:B12,"Q3",T3:T12)+SUMIF(B3:B12,"Q4",T3:T12)
A17: Target DSO/DIO = SMALL(…,2) (2nd-best peer, avoids outlier). Target DPO = LARGE(…,2) (2nd-highest peer). AP Cash Release = positive gap when current DPO < target DPO (company is paying suppliers too early). MAX(…,0) ensures companies already at/beyond benchmark contribute $0.

Sheet Dashboard
A1: Semiconductor WC Benchmarking – Executive Dashboard (All values formula-driven)
A3: SECTION A — Consolidated Metrics Per Company (all values pulled from analysis sheets)
A4: Company | B4: Overall Rank | C4: Quartile | D4: DSO (days) | E4: DIO (days) | F4: DPO (days) | G4: CCC (days) | H4: AR Turns | I4: Inv Turns | J4: CRR (%) | K4: WC ($M) | L4: Op NWC ($M) | M4: WC/Rev (%) | N4: NWC/Rev (%) | O4: Current Ratio | P4: Quick Ratio
A5: =Raw_Data!A3 | B5: =Scoring_Ranking!I3 | C5: =Scoring_Ranking!J3 | D5: =Efficiency_Metrics!H3 | E5: =Efficiency_Metrics!J3 | F5: =Efficiency_Metrics!L3 | G5: =Efficiency_Metrics!M3 | H5: =Efficiency_Metrics!I3 | I5: =Efficiency_Metrics!K3 | J5: =Efficiency_Metrics!N3 | K5: =WC_NWC!D3 | L5: =WC_NWC!J3 | M5: =WC_NWC!F3 | N5: =WC_NWC!K3 | O5: =WC_NWC!L3 | P5: =WC_NWC!M3
A6: =Raw_Data!A4 | B6: =Scoring_Ranking!I4 | C6: =Scoring_Ranking!J4 | D6: =Efficiency_Metrics!H4 | E6: =Efficiency_Metrics!J4 | F6: =Efficiency_Metrics!L4 | G6: =Efficiency_Metrics!M4 | H6: =Efficiency_Metrics!I4 | I6: =Efficiency_Metrics!K4 | J6: =Efficiency_Metrics!N4 | K6: =WC_NWC!D4 | L6: =WC_NWC!J4 | M6: =WC_NWC!F4 | N6: =WC_NWC!K4 | O6: =WC_NWC!L4 | P6: =WC_NWC!M4
A7: =Raw_Data!A5 | B7: =Scoring_Ranking!I5 | C7: =Scoring_Ranking!J5 | D7: =Efficiency_Metrics!H5 | E7: =Efficiency_Metrics!J5 | F7: =Efficiency_Metrics!L5 | G7: =Efficiency_Metrics!M5 | H7: =Efficiency_Metrics!I5 | I7: =Efficiency_Metrics!K5 | J7: =Efficiency_Metrics!N5 | K7: =WC_NWC!D5 | L7: =WC_NWC!J5 | M7: =WC_NWC!F5 | N7: =WC_NWC!K5 | O7: =WC_NWC!L5 | P7: =WC_NWC!M5
A8: =Raw_Data!A6 | B8: =Scoring_Ranking!I6 | C8: =Scoring_Ranking!J6 | D8: =Efficiency_Metrics!H6 | E8: =Efficiency_Metrics!J6 | F8: =Efficiency_Metrics!L6 | G8: =Efficiency_Metrics!M6 | H8: =Efficiency_Metrics!I6 | I8: =Efficiency_Metrics!K6 | J8: =Efficiency_Metrics!N6 | K8: =WC_NWC!D6 | L8: =WC_NWC!J6 | M8: =WC_NWC!F6 | N8: =WC_NWC!K6 | O8: =WC_NWC!L6 | P8: =WC_NWC!M6
A9: =Raw_Data!A7 | B9: =Scoring_Ranking!I7 | C9: =Scoring_Ranking!J7 | D9: =Efficiency_Metrics!H7 | E9: =Efficiency_Metrics!J7 | F9: =Efficiency_Metrics!L7 | G9: =Efficiency_Metrics!M7 | H9: =Efficiency_Metrics!I7 | I9: =Efficiency_Metrics!K7 | J9: =Efficiency_Metrics!N7 | K9: =WC_NWC!D7 | L9: =WC_NWC!J7 | M9: =WC_NWC!F7 | N9: =WC_NWC!K7 | O9: =WC_NWC!L7 | P9: =WC_NWC!M7
A10: =Raw_Data!A8 | B10: =Scoring_Ranking!I8 | C10: =Scoring_Ranking!J8 | D10: =Efficiency_Metrics!H8 | E10: =Efficiency_Metrics!J8 | F10: =Efficiency_Metrics!L8 | G10: =Efficiency_Metrics!M8 | H10: =Efficiency_Metrics!I8 | I10: =Efficiency_Metrics!K8 | J10: =Efficiency_Metrics!N8 | K10: =WC_NWC!D8 | L10: =WC_NWC!J8 | M10: =WC_NWC!F8 | N10: =WC_NWC!K8 | O10: =WC_NWC!L8 | P10: =WC_NWC!M8
A11: =Raw_Data!A9 | B11: =Scoring_Ranking!I9 | C11: =Scoring_Ranking!J9 | D11: =Efficiency_Metrics!H9 | E11: =Efficiency_Metrics!J9 | F11: =Efficiency_Metrics!L9 | G11: =Efficiency_Metrics!M9 | H11: =Efficiency_Metrics!I9 | I11: =Efficiency_Metrics!K9 | J11: =Efficiency_Metrics!N9 | K11: =WC_NWC!D9 | L11: =WC_NWC!J9 | M11: =WC_NWC!F9 | N11: =WC_NWC!K9 | O11: =WC_NWC!L9 | P11: =WC_NWC!M9
A12: =Raw_Data!A10 | B12: =Scoring_Ranking!I10 | C12: =Scoring_Ranking!J10 | D12: =Efficiency_Metrics!H10 | E12: =Efficiency_Metrics!J10 | F12: =Efficiency_Metrics!L10 | G12: =Efficiency_Metrics!M10 | H12: =Efficiency_Metrics!I10 | I12: =Efficiency_Metrics!K10 | J12: =Efficiency_Metrics!N10 | K12: =WC_NWC!D10 | L12: =WC_NWC!J10 | M12: =WC_NWC!F10 | N12: =WC_NWC!K10 | O12: =WC_NWC!L10 | P12: =WC_NWC!M10
A13: =Raw_Data!A11 | B13: =Scoring_Ranking!I11 | C13: =Scoring_Ranking!J11 | D13: =Efficiency_Metrics!H11 | E13: =Efficiency_Metrics!J11 | F13: =Efficiency_Metrics!L11 | G13: =Efficiency_Metrics!M11 | H13: =Efficiency_Metrics!I11 | I13: =Efficiency_Metrics!K11 | J13: =Efficiency_Metrics!N11 | K13: =WC_NWC!D11 | L13: =WC_NWC!J11 | M13: =WC_NWC!F11 | N13: =WC_NWC!K11 | O13: =WC_NWC!L11 | P13: =WC_NWC!M11
A14: =Raw_Data!A12 | B14: =Scoring_Ranking!I12 | C14: =Scoring_Ranking!J12 | D14: =Efficiency_Metrics!H12 | E14: =Efficiency_Metrics!J12 | F14: =Efficiency_Metrics!L12 | G14: =Efficiency_Metrics!M12 | H14: =Efficiency_Metrics!I12 | I14: =Efficiency_Metrics!K12 | J14: =Efficiency_Metrics!N12 | K14: =WC_NWC!D12 | L14: =WC_NWC!J12 | M14: =WC_NWC!F12 | N14: =WC_NWC!K12 | O14: =WC_NWC!L12 | P14: =WC_NWC!M12
A16: SECTION B — Peer Benchmark Summary (Best / Median / Worst — all formulas)
A17: Metric | B17: Best-in-Class [formula] | C17: Peer Median [=MEDIAN] | D17: Peer Average [=AVERAGE] | E17: Worst [formula] | F17: Benchmark Direction
A18: DSO (days) | B18: =MIN(Efficiency_Metrics!H3:Efficiency_Metrics!H12) | C18: =MEDIAN(Efficiency_Metrics!H3:Efficiency_Metrics!H12) | D18: =AVERAGE(Efficiency_Metrics!H3:Efficiency_Metrics!H12) | E18: =MAX(Efficiency_Metrics!H3:Efficiency_Metrics!H12) | F18: Lower = Better
A19: DIO (days) | B19: =MIN(Efficiency_Metrics!J3:Efficiency_Metrics!J12) | C19: =MEDIAN(Efficiency_Metrics!J3:Efficiency_Metrics!J12) | D19: =AVERAGE(Efficiency_Metrics!J3:Efficiency_Metrics!J12) | E19: =MAX(Efficiency_Metrics!J3:Efficiency_Metrics!J12) | F19: Lower = Better
A20: DPO (days) | B20: =MAX(Efficiency_Metrics!L3:Efficiency_Metrics!L12) | C20: =MEDIAN(Efficiency_Metrics!L3:Efficiency_Metrics!L12) | D20: =AVERAGE(Efficiency_Metrics!L3:Efficiency_Metrics!L12) | E20: =MIN(Efficiency_Metrics!L3:Efficiency_Metrics!L12) | F20: Higher = Better
A21: CCC (days) | B21: =MIN(Efficiency_Metrics!M3:Efficiency_Metrics!M12) | C21: =MEDIAN(Efficiency_Metrics!M3:Efficiency_Metrics!M12) | D21: =AVERAGE(Efficiency_Metrics!M3:Efficiency_Metrics!M12) | E21: =MAX(Efficiency_Metrics!M3:Efficiency_Metrics!M12) | F21: Lower = Better
A22: AR Turns | B22: =MAX(Efficiency_Metrics!I3:Efficiency_Metrics!I12) | C22: =MEDIAN(Efficiency_Metrics!I3:Efficiency_Metrics!I12) | D22: =AVERAGE(Efficiency_Metrics!I3:Efficiency_Metrics!I12) | E22: =MIN(Efficiency_Metrics!I3:Efficiency_Metrics!I12) | F22: Higher = Better
A23: Inv Turns | B23: =MAX(Efficiency_Metrics!K3:Efficiency_Metrics!K12) | C23: =MEDIAN(Efficiency_Metrics!K3:Efficiency_Metrics!K12) | D23: =AVERAGE(Efficiency_Metrics!K3:Efficiency_Metrics!K12) | E23: =MIN(Efficiency_Metrics!K3:Efficiency_Metrics!K12) | F23: Higher = Better
A24: CRR (%) | B24: =MAX(Efficiency_Metrics!N3:Efficiency_Metrics!N12) | C24: =MEDIAN(Efficiency_Metrics!N3:Efficiency_Metrics!N12) | D24: =AVERAGE(Efficiency_Metrics!N3:Efficiency_Metrics!N12) | E24: =MIN(Efficiency_Metrics!N3:Efficiency_Metrics!N12) | F24: Higher = Better
A25: WC/Rev (%) | B25: =MIN(WC_NWC!F3:WC_NWC!F12) | C25: =MEDIAN(WC_NWC!F3:WC_NWC!F12) | D25: =AVERAGE(WC_NWC!F3:WC_NWC!F12) | E25: =MAX(WC_NWC!F3:WC_NWC!F12) | F25: Lower = Better
A26: NWC/Rev (%) | B26: =MIN(WC_NWC!K3:WC_NWC!K12) | C26: =MEDIAN(WC_NWC!K3:WC_NWC!K12) | D26: =AVERAGE(WC_NWC!K3:WC_NWC!K12) | E26: =MAX(WC_NWC!K3:WC_NWC!K12) | F26: Lower = Better
A27: Current Ratio | B27: =MAX(WC_NWC!L3:WC_NWC!L12) | C27: =MEDIAN(WC_NWC!L3:WC_NWC!L12) | D27: =AVERAGE(WC_NWC!L3:WC_NWC!L12) | E27: =MIN(WC_NWC!L3:WC_NWC!L12) | F27: ≥1 healthy
A28: Quick Ratio | B28: =MAX(WC_NWC!M3:WC_NWC!M12) | C28: =MEDIAN(WC_NWC!M3:WC_NWC!M12) | D28: =AVERAGE(WC_NWC!M3:WC_NWC!M12) | E28: =MIN(WC_NWC!M3:WC_NWC!M12) | F28: ≥0.8 healthy
A31: SECTION C — Cash Release Potential Summary (all values from Cash_Release sheet)
A32: Scope | B32: AR Cash Release ($M) | C32: Inv Cash Release ($M) | D32: AP Cash Release ($M) | E32: Total Cash Release ($M)
A33: All 10 Companies | B33: =Cash_Release!I14 | C33: =Cash_Release!N14 | D33: =Cash_Release!S14 | E33: =Cash_Release!T14
A34: Q3 + Q4 Laggards only | B34: =Cash_Release!I15 | C34: =Cash_Release!N15 | D34: =Cash_Release!S15 | E34: =Cash_Release!T15
A36: This dashboard is 100% formula-driven — every value references a source cell in Raw_Data, WC_NWC, Efficiency_Metrics, Scoring_Ranking, Benchmark_Analysis, or Cash_Release. Select any cell and inspect the formula bar to trace back to raw data.
